{"isOp":false,"threadNumber":1931372,"number":1931375,"name":"BSO","trip":"!!lUcx6J6dWDQ","id":"5MgKH1+U","time":1507156769000,"time4chanFormatted":"10/04/17(Wed)18:39:29","comment":"“You’re scared of everything, Nel.” You look askance at him.<br><br>“Am not.” He pouts, then grumbles a bit, distracting himself by looking out over the Observatory grounds or checking the message boards on his UI.<br><br>“Hey.” Aelriss’s voice comes from behind you after a quiet few moments, and you look over your shoulder to watch her approach; her characteristic white cloak, hem fluttering around her legs, is now adorned at the hip with a finely-crafted shortsword. Tatsumaki’s with her, too, wearing a form-fitting black bodysuit beneath her light armor. “You two dating now?”<br><br>“I proposed to you already, remember?” You hop to your feet and swivel around, resting against the railing with your arms folded. “You didn’t give me a solid answer.”<br><br>“Sorry, Ashe. Mama said never bring home a DPS.” She shoots you a bare-toothed grin. Tatsumaki is smiling too, but you can’t imagine why since she probably isn’t getting most of this conversation. Maybe she’s just happy to be with her friends.<br><br>“Suit yourself.” You afford a dismissive shrug and a smirk. “Spend your whole life waiting for the one, and you’re gonna be all alone with your bird before you know it.”<br><br>“Joke’s on you; that’s my ideal.” Aelriss says.<br><br>“Weren’t you going to take a break, Ael?” Nel asks.<br><br>“Was.” She responds. “I logged and relogged. It’s not even dark outside where I’m at. Tats says she’s still in if I’m in – so what are y’all doing?”","filename":"Nel.jpg","fileSize":"110 KB","fileSrc":"http://suptg.thisisnotatrueending.com/qstarchive/1931372/thumbs/1507156769477.jpg","fileThumbSrc":"http://suptg.thisisnotatrueending.com/qstarchive/1931372/thumbs/1507156769477s.jpg","md5":"5Prjuts30sNcwYhBrsfIyg==","w":987,"h":1695,"tn_w":72,"tn_h":125}
