{"number":"1953482","threadNumber":"1931372","comment":"<a href=\"#p1953443\" class=\"quotelink\">&gt;&gt;1953443</a><br>We don't only use memories to fight though. Like I said, I'm fine with more HP or PP. When you said tankiness I thought you meant the guardian skill tree which I'm not a fan of. I still think that a sprint/charge or dodge boost would be beneficial in the near future. For when we fight without using our artifact.","time":1507692746000,"time4chanFormatted":"10/10/17(Tue)23:32","id":"3s8dGgyZ","name":"Anonymous","subject":null,"trip":null}
