{"isOp":false,"threadNumber":1978591,"number":1980408,"name":"Anonymous","id":"q0QKSGnz","time":1508294739000,"time4chanFormatted":"10/17/17(Tue)22:45:39","comment":"<a href=\"#p1980390\" class=\"quotelink\">&gt;&gt;1980390</a><br><span class=\"quote\">&gt;&gt; “No problem. Thanks for the advance warning.”</span><br><span class=\"quote\">&gt;Anything Wrong Aelriss or just needing some sleep?</span><br><br><span class=\"quote\">&gt; Ask if anyone’s seen Ayla.</span><br><span class=\"quote\">&gt;message her.</span>"}
