{"isOp":false,"number":"1980651","threadNumber":"1978591","comment":"<a href=\"#p1980647\" class=\"quotelink\">&gt;&gt;1980647</a><br><span class=\"quote\">> Talk about Observers, mentioning the weird thing that happened when you logged in.</span><br><span class=\"quote\">> Talk about Strife Memoriam, and your recent encounter with a ghost.</span><br><span class=\"quote\">> Talk about the Last Argument of Kings, and its potential relation to Hecatel.</span>","time":1508297801000,"time4chanFormatted":"10/17/17(Tue)23:36","id":"sulWMYcI","name":"Anonymous","subject":null,"trip":null}
