{"isOp":false,"number":"1981109","threadNumber":"1978591","comment":"<a href=\"#p1981023\" class=\"quotelink\">&gt;&gt;1981023</a><br><a href=\"#p1981067\" class=\"quotelink\">&gt;&gt;1981067</a><br><a href=\"#p1981042\" class=\"quotelink\">&gt;&gt;1981042</a><br><br>“Only as long as you think it doesn’t.” You respond. “There’s definitely no chance if you just let them win.”<br><br>“I’m not going to try to lose, but my chances don’t look good.” Ayla says.<br><br>“Does anyone else know about all this, Ayla?” You ask.<br><br>“You’re the only one as of now.” She responds. “I was just about to put Dorian in charge and appoint new moderators for the message boards, just in case. I’d hate to leave behind a mess.”<br><br>You sigh as you look around the room – at Ayla, and at all of the machine parts, the scattered notes, and the drill bathed in soft blue light from the workshop floor. You imagine what lies above, and what lies below, and feel as if you are missing something – and as if you are being watched.<br><br><s>Done for tonight. Thanks for the replies.</s>","time":1508305809000,"time4chanFormatted":"10/18/17(Wed)1:50","id":"FZtRkOsu","name":"BSO","subject":null,"trip":"!!lUcx6J6dWDQ","filename":"original_314840_QKR1Gac3r3n_jN8HGn_Y6k8Rn.jpg","fileSize":"4206645 B","fileSrc":"http://suptg.thisisnotatrueending.com/qstarchive/1978591/images/1508305809810.jpg","fileThumbSrc":"http://suptg.thisisnotatrueending.com/qstarchive/1978591/thumbs/1508305809810s.jpg","md5":"vZUsP+YEo7as+P6xW0cltg==","w":"5000","h":"2130","tn_w":"125","tn_h":"53"}
