{"isOp":false,"number":"1984448","threadNumber":"1978591","comment":"<a href=\"#p1984435\" class=\"quotelink\">&gt;&gt;1984435</a><br><span class=\"quote\">>> “Arty sounds good. We lost ours, so.”</span><br><span class=\"quote\">> Forge reinforced moltensteel bulwark for 1000#, tempered chitin plate x2, aethersteel bar x2 [[ + Fireproof Defense ]] [[ + Durability Up ]]</span>","time":1508386473000,"time4chanFormatted":"10/19/17(Thu)0:14","id":"sf9WD30I","name":"Anonymous","subject":null,"trip":null}
