{"isOp":false,"number":"1986032","threadNumber":"1978591","comment":"<a href=\"#p1986012\" class=\"quotelink\">&gt;&gt;1986012</a><br>True but it's gonna be split between 5 people. <br><a href=\"#p1986016\" class=\"quotelink\">&gt;&gt;1986016</a><br>I assume it means we'll be able to use its powers without the mental influence it seems to have when a memory is activated. I can only speculate that we can Exalt it to boost a memory's power without decreasing its mental effect on us if we address the nature of the memory and find out that it's not so bad.","time":1508449610000,"time4chanFormatted":"10/19/17(Thu)17:46","id":"SVVGR2zr","name":"Anonymous","subject":null,"trip":null}
