{"isOp":false,"number":3402363,"threadNumber":3395258,"comment":"<a href=\"#p3402340\" class=\"quotelink\">&gt;&gt;3402340</a><br>True.<br><a href=\"#p3402344\" class=\"quotelink\">&gt;&gt;3402344</a><br><span class=\"quote\">&gt; Find a hiding place in the underground and have Nel or Aelriss do any shopping for you, then meet later.</span><br><span class=\"quote\">&gt; Accept Freya’s contact request and add her to the group chat.</span><br>We need some antidotes and more hp potions.","time":1554246834000,"time4chanFormatted":"04/02/19(Tue)19:13:54","id":"kWh+TW52","name":"Anonymous"}
