{"number":3403240,"threadNumber":3395258,"comment":"<b>Rolled 80 (1d100)<br><br></b><a href=\"#p3403231\" class=\"quotelink\">&gt;&gt;3403231</a><br>I concur. We&#039;ll see.<br><br><a href=\"#p3403235\" class=\"quotelink\">&gt;&gt;3403235</a><br>Bets on Kainzo being here and going for our head while we&#039;re contained in this small PvP enabled space?<br><br><s>Rolling to crisp that motherfucker with the Prophet of Flame in this PvP enabled box when he shows up.</s>","time":1554267733000,"time4chanFormatted":"04/03/19(Wed)01:02:13","id":"V2h2oypP","name":"Anonymous"}
