{"isOp":false,"threadNumber":3395258,"number":3407628,"name":"Anonymous","id":"Q8YeT3t2","time":1554422155000,"time4chanFormatted":"04/04/19(Thu)19:55:55","comment":"<a href=\"#p3407603\" class=\"quotelink\">&gt;&gt;3407603</a><br><span class=\"quote\">&gt;“Do we know of anything else that can affect players in safe zones?”</span><br><span class=\"quote\">&gt;\"Florica's concerns are valid, but it seems I have the option to prevent the memories of my enemies from taking control - you actually found me whilst I was doing just that for one of them.\"</span><br><span class=\"quote\">&gt;\"Whilst I'm uncertain as to the extent of my powers as they are now I am confident I am in control of my avatar again.\"</span><br><span class=\"quote\">&gt;\"I'm sure you're busy but there's definitely a spot for a kickass flying spear user beside me when I head down to confront Tethis.\"</span>"}
