{"isOp":false,"threadNumber":3437745,"number":3438764,"name":"Sylv","trip":"!!osgMMlm58hs","id":"zQdneY4M","time":1555395456000,"time4chanFormatted":"04/16/19(Tue)02:17:36","comment":"<span class=\"mu-r\"><span class=\"mu-s\"> ⟦ LESSER ART: DARK METAMORPHOSIS ⟧ </span></span><br><br>Unusually-familiar screaming issues from Freya’s wounds. She swipes the Hand across her field of view as if to push the whole of the world aside; borrowed life becomes boundary-light, formed into a hideous claw that lurches from just out of sight. It collides with Florica, catching her off-guard, and sending her careening across the cavern. The Diabolique flies from her hand, sliding a distance away from her.<br><br>“Ascheritte, please.” Freya struggles to stand, balancing on her scythe. She looks to the cavern behind her, then to the ceiling high above, as if checking for enemies. “Tell her to stop. All of us are going to die down here.”<br><br><span class=\"quote\">&gt; Implore the two of them to call it off.</span><br><span class=\"quote\">&gt; Tell them to sort it out themselves, then heal up and head off.</span><br><span class=\"quote\">&gt; Tell Nel and Aelriss to keep them in line, then heal up and head off.</span><br><span class=\"quote\">&gt; Other. (Write-in.)</span>","filename":"1480130065966.jpg","fileSize":"308 KB","fileSrc":"http://suptg.thisisnotatrueending.com/qstarchive/3437745///i.4cdn.org/qst/1555395456809.jpg","fileThumbSrc":"http://suptg.thisisnotatrueending.com/qstarchive/3437745///i.4cdn.org/qst/1555395456809s.jpg","md5":"hv2E3ptsyX1BsSlFKFTMLg==","w":1920,"h":1127,"tn_w":125,"tn_h":73}
