{"isOp":false,"threadNumber":3437745,"number":3438386,"name":"Anonymous","id":"aeu9tEXi","time":1555381539000,"time4chanFormatted":"04/15/19(Mon)22:25:39","comment":"<a href=\"#p3438380\" class=\"quotelink\">&gt;&gt;3438380</a><br>I mean, a long time ago he did post this on his ask.fm<br><br><span class=\"quote\">&gt; What's broken sky online?</span><br><span class=\"quote\">&gt;An old forum RP I used to run with a few friends. I kept the email because I liked the name.</span><br><br>So was it ever meant to be a secret?"}
