{"isOp":false,"number":"37693091","threadNumber":"37686014","comment":"<a href=\"#p37692957\" class=\"quotelink\">&gt;&gt;37692957</a><br>Let's consider this, he is a friend of Circe we killed Circe. I think telling him is a good way to make an enemy or he might already know and plan on screwing us over in the ruins<br><br><span class=\"quote\">>Decline</span><br>Let's go sell our ill gotten loot and get some nicer gear first<br><br><span class=\"quote\">>Ask Nel about the Disposable Heroes or those weirdo roleplayers. </span><br><br>we gotta find us some semi-permanent allies","time":1422505518000,"time4chanFormatted":"1/28/15(Wed)23:25","id":null,"name":"Anonymous","subject":null,"trip":null}
