{"isOp":false,"threadNumber":37686014,"number":37695055,"name":"Anonymous","time":1422510828000,"time4chanFormatted":"01/29/15(Thu)00:53:48","comment":"<a href=\"#p37694969\" class=\"quotelink\">&gt;&gt;37694969</a><br><span class=\"quote\">&gt;Investigate the Materialization Altar</span><br><a href=\"#p37694988\" class=\"quotelink\">&gt;&gt;37694988</a><br>Forgot to say that our main offensive capabilities will come from the tech we use.<s>or we can go backwards and focus on offense, while we use tech as a defense.</s>"}
