{"isOp":false,"number":"37691878","threadNumber":"37686014","comment":"<a href=\"#p37691764\" class=\"quotelink\">&gt;&gt;37691764</a><br>Go meet find the rogue from before. What class is he, anyways? Go talk about joining up with the Guardians.<br><br>Also, I'm going to say that we just stick with sabers for now, until we find a bit more about it. On that note, let's start asking around and seeing what it takes to get our scimitar identified.","time":1422502357000,"time4chanFormatted":"1/28/15(Wed)22:32","id":null,"name":"Anonymous","subject":null,"trip":null}
