{"isOp":false,"number":"37739151","threadNumber":"37731816","comment":"<a href=\"#p37739089\" class=\"quotelink\">&gt;&gt;37739089</a><br><span class=\"quote\">>Chug potion</span><br>Massive priority, cannot risk another surprise attack<br><span class=\"quote\">>Switch our damaged scimitar out for the other one</span><br>Might be quick to do if we've already grabbed a potion from our UI, otherwise not important<br><span class=\"quote\">>Go save Rhett</span>","time":1422681624000,"time4chanFormatted":"1/31/15(Sat)0:20","id":null,"name":"Anonymous","subject":null,"trip":null}
