{"isOp":false,"threadNumber":38429954,"number":38430594,"name":"Anonymous","time":1425342634000,"time4chanFormatted":"03/02/15(Mon)19:30:34","comment":"<a href=\"#p38430540\" class=\"quotelink\">&gt;&gt;38430540</a><br>Vision wasn't interested was he? One way or another we'd come to conclude that he wasn't coming along.<br><br>For which I'm a little glad, he was getting worrisome regarding the allure of celestial gems.","filename":"mesteacan2.jpg","fileSize":"49 KB","fileSrc":"http://suptg.thisisnotatrueending.com/archive/38429954/images/1425342634257.jpg","fileThumbSrc":"http://suptg.thisisnotatrueending.com/archive/38429954/images/1425342634257s.jpg","md5":"xSq8a1X0JR4wPiNMs9ov3w==","w":300,"h":409,"tn_w":91,"tn_h":125}
