{"number":"40007722","threadNumber":"40003078","comment":"<a href=\"#p40007606\" class=\"quotelink\">&gt;&gt;40007606</a><br>\"She might be only dangerous in certain specific contexts. I'm pretty sure she's lore significant, being that she looks like the lady in the portrait, and that notes on resurrecting the dead, context indicates that she's the lost love Kjorkos attempted to bring to life. Maybe she's a support monster when we fight Kjorikos, or maybe even we're supposed to team up with her and she's meant to fight Kjorikos in the old 'rebel against your mad scientist creator' thing.\"","time":1431844275000,"time4chanFormatted":"5/17/15(Sun)2:31","id":null,"name":"Anonymous","subject":null,"trip":null}
