{"isOp":false,"threadNumber":44309252,"number":44313823,"name":"Sylvetica","trip":"!3c0YaXQPuY","time":1450755345000,"time4chanFormatted":"12/21/15(Mon)22:35:45","comment":"<a href=\"#p44313752\" class=\"quotelink\">&gt;&gt;44313752</a><br><br>You sell your starting boots and pants for a whopping fifty credits, to a total of 179. You wonder, for approximately three seconds, if anyone's ever sold their pants to buy a potion.<br><br>“One more thing, before I go.” You say. “Could I combine these plates and armor scraps to make a light shield? Or apply worm teeth to my boots for better climbing?”<br><br>“You would not be satisfied with either result.” It says. “Those armor scraps could be used to decorate, or perhaps enhance, a small shield or a weapon such as a dagger or knife. Not even my great skill can predict the results, and cannot promise they would be more than cosmetic.”<br><br>[[ 1 ]]<br><span class=\"quote\">&gt; Respond to Liza. (Write-in.)</span><br><span class=\"quote\">&gt; Ignore Liza or send someone else a message. (Write-in.)</span><br><br>[[ 2 ]]<br><span class=\"quote\">&gt; Decorate wooden buckler with gilded armor scraps for 75#.</span><br><span class=\"quote\">&gt; Sell gilded armor scraps for 100#.</span><br><span class=\"quote\">&gt; Leave the Aetherforge.</span>","filename":"84129481.jpg","fileSize":"90 KB","fileSrc":"http://suptg.thisisnotatrueending.com/archive/44309252/images/1450755345576.jpg","fileThumbSrc":"http://suptg.thisisnotatrueending.com/archive/44309252/images/1450755345576s.jpg","md5":"IWAIpQfpGzEg/bsCbfrX2A==","w":1023,"h":653,"tn_w":125,"tn_h":79}
