{"isOp":false,"threadNumber":44309252,"number":44313863,"name":"Anonymous","time":1450755466000,"time4chanFormatted":"12/21/15(Mon)22:37:46","comment":"<a href=\"#p44313767\" class=\"quotelink\">&gt;&gt;44313767</a><br>seems I need to elaborate<br><br><a href=\"#p44313674\" class=\"quotelink\">&gt;&gt;44313674</a><br>I don't want to invest all those points into STR dual-wielding. EVEN IF we found a fighting style that uses two heavy weapons of similar(because they both need to be big to be heavy) size that makes more sense than sword-chucks, the XP and gear investment would leave us slowly losing tank status and entering glass canon."}
