{"isOp":false,"number":"44363913","threadNumber":"44363193","comment":"<a href=\"#p44363863\" class=\"quotelink\">&gt;&gt;44363863</a><br><span class=\"quote\">> Slay the Lotus King.</span><br><span class=\"quote\">>Examine Aura Brush (wielded, soulbound, 35 PP committed)</span><br>and<br><span class=\"quote\">>enchanter’s aethersteel rod (alternate weapon, worn on belt, empowered by Earth: chthonian skull)</span>","time":1450994985000,"time4chanFormatted":"12/24/15(Thu)17:09","id":null,"name":"Anonymous","subject":null,"trip":null}
