{"isOp":false,"number":"44368421","threadNumber":"44363193","comment":"<a href=\"#p44368375\" class=\"quotelink\">&gt;&gt;44368375</a><br>“You’re telling us this, why?” You ask.<br><br>“Because I’m bored.” Anaximander shrugs.<br><br>“You can’t be serious.” You shake your head, reaching for the Aura Brush. You’ve had enough.<br><br>“You’re right, I’m joking. It’s because all of us are on the same team, no matter how much you like it, and even if everyone seems to be afflicted with the strange idea that I’m an ‘asshole’.” He grins. It's enough to stay your hand, but it won't stay that way for more than a few seconds if he doesn't keep it up.<br><br>So he continues. “I’m here right now to figure out why anyone would want to stop people from getting to the surface, which is something I’m sure we’re all wondering at least a little. Now, ration this out with me: assuming that information is no longer private, it is figuratively impossible for me to stop you from finding it out. I mean, IN THEORY, I could pull out my sword and try to kill both of you right here, but we all know that would end with the insides of my head splattered all over the wall right there. And, yes, I can be a bit reckless, but I’m not what you’d call suicidal.”","time":1451015232000,"time4chanFormatted":"12/24/15(Thu)22:47","id":null,"name":"BSO","subject":null,"trip":"!3c0YaXQPuY","filename":"Hecatel.jpg","fileSize":"358812 B","fileSrc":"http://suptg.thisisnotatrueending.com/qstarchive/44363193/images/1451015232566.jpg","fileThumbSrc":"http://suptg.thisisnotatrueending.com/qstarchive/44363193/thumbs/1451015232566s.jpg","md5":"e8Pa1wNON4myXSpWpe5plA==","w":"1024","h":"1474","tn_w":"86","tn_h":"125"}
