{"number":"44367251","threadNumber":"44363193","comment":"<a href=\"#p44367222\" class=\"quotelink\">&gt;&gt;44367222</a><br><span class=\"quote\">> [[ Underground: Nypha Monastery – Hall of Seasons // PVP Disabled ]]</span><br><br>The place around you is decorated in keeping with its name. You feel the temperature change as you pass through Spring, Summer, and Fall—at last, in Winter, feet crunching in the snow. The robed NPCs hide behind columns and in corners, cowering in fear of you as you make your way to the Lotus King’s sacred hall.<br><br>The room below is dark. Against the wall, a statue is carved out of a house-sized pyrite crystal erupting from the earth. It depicts a child on his knees, offering a single lotus bloom to the heavens in both hands. A bowl awaits on the pedestal above him.<br><br><span class=\"quote\">> [[ Greater Celestial Materialization Altar ]]</span><br><span class=\"quote\">> Celestial Manifestation “Nypha Monastery”</span><br><span class=\"quote\">> MANIFESTATION GRANTED BY:</span><br>a Precursor, “…”<br><span class=\"quote\">> [[ Offer Celestial Gems ]]</span><br>* Create Celestial Artifact<br>* Enhance Celestial Artifact<br>* Empower Mundane Item<br>* Enhance Celestial Manifestation<br>* Destroy Celestial Manifestation (To The Victors Go The Spoils)<br><span class=\"quote\">> [[ Offer Item ]]</span><br>* Offer an Item to the Celestials<br><br><span class=\"quote\">> [[ Continued ]]</span>","time":1451009909000,"time4chanFormatted":"12/24/15(Thu)21:18","id":null,"name":"BSO","subject":null,"trip":"!3c0YaXQPuY"}
