{"isOp":false,"number":"44365926","threadNumber":"44363193","comment":"<a href=\"#p44365809\" class=\"quotelink\">&gt;&gt;44365809</a><br><span class=\"quote\">>> Attempt to outmaneuver him, striking from a different angle.</span><br><span class=\"quote\">>> Another blast. Dethrone the King in one fell swoop.</span><br><span class=\"quote\">>>>44365839 # >>44365910 #</span><br><span class=\"quote\">>...Anonymous </span><br><span class=\"quote\">>12/24/15(Thu)19:28:34 No.44365839</span><br><span class=\"quote\">>>>44365809 #</span><br><span class=\"quote\">>>> Attempt to outmaneuver him, striking from a different angle.</span><br>Pandora is like Deidara","time":1451003703000,"time4chanFormatted":"12/24/15(Thu)19:35","id":null,"name":"Anonymous","subject":null,"trip":null}
