{"isOp":false,"number":"44515902","threadNumber":"44507775","comment":"So right now, im leaning on totem, with one utility artifact later, depending on what happens.<br><br>But does anyone think it wise to grab the Shaper before that, never upgrading? Build up new locations/paths a little at a time after every dungeon run/log out, or just use it as a really expensive pickaxe if we lack an explorer.","time":1451716728000,"time4chanFormatted":"1/2/16(Sat)1:38","id":null,"name":"Anonymous","subject":null,"trip":null}
