{"isOp":false,"threadNumber":46550137,"number":46573866,"name":"Anonymous","time":1460245937000,"time4chanFormatted":"04/09/16(Sat)19:52:17","comment":"<a href=\"#p46573689\" class=\"quotelink\">&gt;&gt;46573689</a><br>If you're not trolling It basically causes a causality glitch. <br><br><br>Steps A&gt;B&gt;C?<br>with king crimson it's<br>A&gt;C<br><br>Is t causes the interevening time to happen successfully without the time in between actually happening. Say the guy you want to stab is behind a disintegration field?<br>A. Charge<br>B. Go through field(die)<br>C. Stab him<br><br>it'd skip B but still have the positive effects happen."}
