{"number":"584190","threadNumber":"580189","comment":"<a href=\"#p584123\" class=\"quotelink\">&gt;&gt;584123</a><br>Hey, I'm not saying it's a smart idea. But it is most definitely a very Ascheritte idea. Just think about all the things that could go right, then stop your line of thinking there and do it.<br><br>But yeah, those poison spike chains and the bottle are all ranged so we could fall back even if it turned out to be something raid-tier.","time":1474125862000,"time4chanFormatted":"9/17/16(Sat)11:24","id":"gQ86Sn8a","name":"Anonymous","subject":null,"trip":null}
