{"isOp":false,"threadNumber":580189,"number":586644,"name":"BSO","trip":"!3c0YaXQPuY","id":"tXyxxgeA","time":1474157022000,"time4chanFormatted":"09/17/16(Sat)20:03:42","comment":"“Then it looks like it’s our responsibility to take care of it.” You nod. “My Artifact is ready, and it’ll hit pretty hard. Can anyone stop bleeding?”<br><br>Smith tosses you a roll of bandages, and you don’t hesitate to apply them. Your bleeding stops, and you gradually begin to recover health.<br><br><span class=\"quote\">&gt; [[ HP: 20 / 35 ]]</span><br><br>You can see something over the rocks. At least twice your height, it resembles a starving ogre, built broad and muscular, but with skin pulled taut against its joints. Its head is bound in a strange sort of helmet that resembles a spiked iron cage. It’s stomping closer, heavy footsteps dislodging dust and bits of rock from above. You hear chains rattling. The shouting of the distant raid party echoes from far below at the base of the cliff you’re standing on.<br><br>Tatsumaki is already moving forward, while the other four of you remain in formation.<br><br><span class=\"quote\">&gt; [[ Strife Memoriam: Rust ]] Unleash your strength.</span><br><span class=\"quote\">&gt; Move up with Tatsumaki.</span><br><span class=\"quote\">&gt; Have the party spread out and attack from multiple angles.</span><br><span class=\"quote\">&gt; Write-in.</span>"}
