{"isOp":false,"threadNumber":949671,"number":954670,"name":"Anonymous","id":"DqEsHyZb","time":1482122075000,"time4chanFormatted":"12/18/16(Sun)23:34:35","comment":"<a href=\"#p954631\" class=\"quotelink\">&gt;&gt;954631</a><br><span class=\"quote\">&gt;Multiple uses</span><br><span class=\"quote\">&gt;swap on the fly</span><br>How about this:<br><br>it stores 2 memories at a time, and we can use each memory once.<br><br>Might not be compatible with the way the cooldown works, but it'd be kinda like cycling.<br><br>After that, I'm thinking either reducing commit PP or getting a utility/defensive artifact."}
