{"number":"982299","threadNumber":"980053","comment":"<a href=\"#p982292\" class=\"quotelink\">&gt;&gt;982292</a><br><br>Though doing so can’t be done anonymously, <span class=\"mu-i\">anyone</span> could have a bounty placed on their head for any price.<br><br>You ration there’s no way to stop it, barring a single guild monopolizing control of entire zones and disabling PVP. Perhaps, you think, the power of Celestial Gems, in their luster and allure, could pose a different means of putting an end to it – though perhaps it’s these Gems that drives the Identified to hunt one another down in the first place.<br><br>You think about Candrence, the imposing Artifact user from the meeting at the Observatory before the raid. She's one of the esteemed bounty hunters - and it seemed she was quite proud of it. You're not sure about your place in any of this; you can't imagine what she'd have to say...<br><br><span class=\"quote\">> [[ Contact Request: Kengo ]]</span><br><br>Your UI pings. A message window emerges in front of your browser.<br><br><span class=\"quote\">> [[ UI Messenger – Kengo ]]</span><br><span class=\"quote\">> [[ Kengo ]]: Yo.</span><br><span class=\"quote\">> [[ Kengo ]]: You’re the guy that’s supposed to be waiting on me?</span><br><span class=\"quote\">> [[ Ascheritte ]]: Well, that’s what Liza said.</span><br><span class=\"quote\">> [[ Ascheritte ]]: So, apparently.</span><br><span class=\"quote\">> [[ Kengo ]]: Well we’re on our way down in a big way.</span><br><span class=\"quote\">> [[ Kengo ]]: The spider-slaughter has already begun.</span><br><span class=\"quote\">> [[ Kengo ]]: You are still pretty far underground though.</span><br><span class=\"quote\">> [[ Ascheritte ]]: You don’t say?</span><br><span class=\"quote\">> [[ Kengo ]]: Oh, hush.</span><br><span class=\"quote\">> [[ Kengo ]]: Just give us a bit, mmk?</span>","time":1482907581000,"time4chanFormatted":"12/28/16(Wed)1:46","id":"XrT+CxR1","name":"BSO","subject":null,"trip":"!3c0YaXQPuY","filename":"Kengo.jpg","fileSize":"72732 B","fileSrc":"http://suptg.thisisnotatrueending.com/qstarchive/980053/images/1482907581545.jpg","fileThumbSrc":"http://suptg.thisisnotatrueending.com/qstarchive/980053/thumbs/1482907581545s.jpg","md5":"vqHSvMrj/fCgikK3zJ4/jg==","w":"700","h":"760","tn_w":"115","tn_h":"125"}
